asakpy/__init__.py
asakpy-1.1.0.dist-info/METADATA
asakpy-1.1.0.dist-info/WHEEL
asakpy-1.1.0.dist-info/top_level.txt
asakpy-1.1.0.dist-info/RECORD
